<?xml version = '1.0' encoding = 'UTF-8'?>
<TableProxySqlServerv2k5 class="oracle.dbtools.crest.model.design.storage.sqlserver.v2k5.TableProxySqlServerv2k5" name="Tuning" directorySegmentName="seg_0" id="C2F32D49-321D-93CF-D082-3E1C6AF74040">
<createdBy>MichalBonino</createdBy>
<createdTime>2024-04-29 23:41:56 UTC</createdTime>
<ownerDesignName>MCRISSLegacy</ownerDesignName>
<schemaObject>2A6D9360-3BB2-5CEA-6E99-790D76996FDF</schemaObject>
<database>7220F1F8-DA6B-58D6-61AE-B77688E1C655</database>
<schema>CEC76C37-9D45-8E15-510C-CBE87FFE10F5</schema>
<columnProxies>
<ColumnProxy class="oracle.dbtools.crest.model.design.storage.sqlserver.v2k12.ColumnProxySqlServerv2k12" name="HostName" id="06DCBCD4-39B7-0947-B3D0-806B347FD3F6">
<createdBy>MichalBonino</createdBy>
<createdTime>2024-04-29 23:42:11 UTC</createdTime>
<ownerDesignName>MCRISSLegacy</ownerDesignName>
</ColumnProxy>
<ColumnProxy class="oracle.dbtools.crest.model.design.storage.sqlserver.v2k12.ColumnProxySqlServerv2k12" name="LoginName" id="37542658-9747-379F-2DE3-F9E51A76462F">
<createdBy>MichalBonino</createdBy>
<createdTime>2024-04-29 23:42:11 UTC</createdTime>
<ownerDesignName>MCRISSLegacy</ownerDesignName>
</ColumnProxy>
<ColumnProxy class="oracle.dbtools.crest.model.design.storage.sqlserver.v2k12.ColumnProxySqlServerv2k12" name="EventClass" id="43DF6A63-006A-D12C-41D6-3EE7AA8E3123">
<createdBy>MichalBonino</createdBy>
<createdTime>2024-04-29 23:42:10 UTC</createdTime>
<ownerDesignName>MCRISSLegacy</ownerDesignName>
</ColumnProxy>
<ColumnProxy class="oracle.dbtools.crest.model.design.storage.sqlserver.v2k12.ColumnProxySqlServerv2k12" name="StartTime" id="5A2A3CB1-A41B-10F4-C01D-0199DADC1C47">
<createdBy>MichalBonino</createdBy>
<createdTime>2024-04-29 23:42:11 UTC</createdTime>
<ownerDesignName>MCRISSLegacy</ownerDesignName>
</ColumnProxy>
<ColumnProxy class="oracle.dbtools.crest.model.design.storage.sqlserver.v2k12.ColumnProxySqlServerv2k12" name="RowNumber" id="8B4A20DE-8DF7-CF43-1C7B-65ACE92DF431">
<createdBy>MichalBonino</createdBy>
<createdTime>2024-04-29 23:42:10 UTC</createdTime>
<ownerDesignName>MCRISSLegacy</ownerDesignName>
<asIdentity>true</asIdentity>
<identityForReplication>YES</identityForReplication>
</ColumnProxy>
<ColumnProxy class="oracle.dbtools.crest.model.design.storage.sqlserver.v2k12.ColumnProxySqlServerv2k12" name="Dura.on" id="95D18964-A28F-B5EC-6820-F6FF64B1F1D2">
<createdBy>MichalBonino</createdBy>
<createdTime>2024-04-29 23:42:10 UTC</createdTime>
<ownerDesignName>MCRISSLegacy</ownerDesignName>
</ColumnProxy>
<ColumnProxy class="oracle.dbtools.crest.model.design.storage.sqlserver.v2k12.ColumnProxySqlServerv2k12" name="EndTime" id="A0F12766-70B5-8E95-69A8-88BAD376CD9B">
<createdBy>MichalBonino</createdBy>
<createdTime>2024-04-29 23:42:11 UTC</createdTime>
<ownerDesignName>MCRISSLegacy</ownerDesignName>
</ColumnProxy>
<ColumnProxy class="oracle.dbtools.crest.model.design.storage.sqlserver.v2k12.ColumnProxySqlServerv2k12" name="DatabaseID" id="A38CC226-F44F-172C-8466-C3074ADD1DD4">
<createdBy>MichalBonino</createdBy>
<createdTime>2024-04-29 23:42:11 UTC</createdTime>
<ownerDesignName>MCRISSLegacy</ownerDesignName>
</ColumnProxy>
<ColumnProxy class="oracle.dbtools.crest.model.design.storage.sqlserver.v2k12.ColumnProxySqlServerv2k12" name="SPID" id="C6FFF1D0-CE1E-29A0-A867-858EF73D1F23">
<createdBy>MichalBonino</createdBy>
<createdTime>2024-04-29 23:42:11 UTC</createdTime>
<ownerDesignName>MCRISSLegacy</ownerDesignName>
</ColumnProxy>
<ColumnProxy class="oracle.dbtools.crest.model.design.storage.sqlserver.v2k12.ColumnProxySqlServerv2k12" name="DatabaseName" id="D9220158-5DDF-0971-0BF9-F0B9F29A333A">
<createdBy>MichalBonino</createdBy>
<createdTime>2024-04-29 23:42:11 UTC</createdTime>
<ownerDesignName>MCRISSLegacy</ownerDesignName>
</ColumnProxy>
<ColumnProxy class="oracle.dbtools.crest.model.design.storage.sqlserver.v2k12.ColumnProxySqlServerv2k12" name="TextData" id="EED7AA2E-D50F-39D0-1267-31ECDE1AF085">
<createdBy>MichalBonino</createdBy>
<createdTime>2024-04-29 23:42:10 UTC</createdTime>
<ownerDesignName>MCRISSLegacy</ownerDesignName>
</ColumnProxy>
</columnProxies>
<primaryKeys>
<PrimaryKey class="oracle.dbtools.crest.model.design.storage.sqlserver.v2k5.PKProxySqlServerv2k5" name="PK__Tuning__5F43C5EB" id="4513F591-28C2-4829-FF70-740A4110A398">
<createdBy>MichalBonino</createdBy>
<createdTime>2024-04-29 23:42:11 UTC</createdTime>
<ownerDesignName>MCRISSLegacy</ownerDesignName>
<clustered>true</clustered>
<fillFactor>100</fillFactor>
<partitioningColumn>2FF15892-B920-E76B-1E84-0BD4FA3D9EDB</partitioningColumn>
</PrimaryKey>
</primaryKeys>
</TableProxySqlServerv2k5>