<?xml version = '1.0' encoding = 'UTF-8'?>
<StoredProcedureSqlServerv2k5 class="oracle.dbtools.crest.model.design.storage.sqlserver.v2k5.StoredProcedureSqlServerv2k5" name="[GetCoun.es]" directorySegmentName="seg_5" id="7223DF21-F938-5BBC-F834-3C53E3B51951">
<sourceDDLFile>Appian.sql</sourceDDLFile>
<createdBy>MichalBonino</createdBy>
<createdTime>2024-04-29 23:57:48 UTC</createdTime>
<ownerDesignName>MCRISSLegacy</ownerDesignName>
<body><![CDATA[( 
  @StateCode varchar(3) 
 ) 
AS 
 
SELECT ID, Code, [Name] 
FROM [USMC].[vwCoun.es] WITH (NOLOCK) 
WHERE StateCode = @StateCode 
ORDER BY [Name]]]></body>
<schema>E9C4E37D-78A2-31F9-D580-7C2848ACFCB7</schema>
<database>EA42DEDC-DFC5-B775-3079-AD0E133F5E1D</database>
</StoredProcedureSqlServerv2k5>