<?xml version = '1.0' encoding = 'UTF-8'?>
<TableProxySqlServerv2k5 class="oracle.dbtools.crest.model.design.storage.sqlserver.v2k5.TableProxySqlServerv2k5" name="MEPS_SON_MAP" directorySegmentName="seg_2" id="237F8A68-C181-C6C8-876A-9C996E30935D">
<createdBy>MichalBonino</createdBy>
<createdTime>2024-04-29 19:29:13 UTC</createdTime>
<ownerDesignName>MCRISSLegacy</ownerDesignName>
<schemaObject>2A6D9360-3BB2-5CEA-6E99-790D76996FDF</schemaObject>
<database>B007042D-D2E3-F83F-481F-CEB23B21CB30</database>
<filegroup>E6573514-5674-5781-6648-B1C5FB42B0A5</filegroup>
<schema>3925E19F-DC76-90A4-B892-D7A526C79632</schema>
<columnProxies>
<ColumnProxy class="oracle.dbtools.crest.model.design.storage.sqlserver.v2k12.ColumnProxySqlServerv2k12" name="MEPS_ORGANIZATION_ID" id="2419EBF9-C3FE-9468-35D1-915A22C42BF7">
<createdBy>MichalBonino</createdBy>
<createdTime>2024-04-29 19:29:23 UTC</createdTime>
<ownerDesignName>MCRISSLegacy</ownerDesignName>
</ColumnProxy>
<ColumnProxy class="oracle.dbtools.crest.model.design.storage.sqlserver.v2k12.ColumnProxySqlServerv2k12" name="SON" id="ED3A8464-707A-7978-E223-6315F306C247">
<createdBy>MichalBonino</createdBy>
<createdTime>2024-04-29 19:29:23 UTC</createdTime>
<ownerDesignName>MCRISSLegacy</ownerDesignName>
</ColumnProxy>
</columnProxies>
<primaryKeys>
<PrimaryKey class="oracle.dbtools.crest.model.design.storage.sqlserver.v2k5.PKProxySqlServerv2k5" name="PK_MEPS_SON_MAP" id="0B5A895A-4FE7-0421-F276-495A0F869CDD">
<createdBy>MichalBonino</createdBy>
<createdTime>2024-04-29 19:29:23 UTC</createdTime>
<ownerDesignName>MCRISSLegacy</ownerDesignName>
<clustered>true</clustered>
<fileGroup>E6573514-5674-5781-6648-B1C5FB42B0A5</fileGroup>
<partitioningColumn>045DADA6-8428-B2A3-030E-66C752BAC0AA</partitioningColumn>
</PrimaryKey>
</primaryKeys>
</TableProxySqlServerv2k5>