<?xml version = '1.0' encoding = 'UTF-8'?>
<FKIndexAssociation class="oracle.dbtools.crest.model.design.relational.FKIndexAssociation" directorySegmentName="seg_2" id="3780162F-35C2-1927-F7A2-9A93BA09EFB9" containerWithKeyObject="7785C66E-6D90-1310-D310-E98C7E074B6D" localFKIndex="3D7A3B40-2C36-410A-7394-E1CCAA7CDFEA" name="FK_TrainingEvalua.on_TrainingFile">
<sourceDDLFile>create RSSOSS script - MCRISS OTA.txt</sourceDDLFile>
<createdBy>MichalBonino</createdBy>
<createdTime>2024-04-29 23:42:13 UTC</createdTime>
<ownerDesignName>MCRISSLegacy</ownerDesignName>
<importedID>DC6C700E-1824-F049-EBD8-27EEB9C63E64</importedID>
<referredTableLongName>USMC.TrainingFile</referredTableLongName>
<deleteRule>NO ACTION</deleteRule>
<referredTableID>FF189968-611A-5CFB-C105-90D3A1C08614</referredTableID>
<keyObject>9509C0E4-E899-DF0F-BC0F-E606E309A999</keyObject>
<referredKeyID>9509C0E4-E899-DF0F-BC0F-E606E309A999</referredKeyID>
<mandatory>true</mandatory>
<refColNames>ID</refColNames>
<transferable>true</transferable>
<rely>false</rely>
<columnDependencyConstraintGenerateInDDL>true</columnDependencyConstraintGenerateInDDL>
</FKIndexAssociation>