<?xml version = '1.0' encoding = 'UTF-8'?>
<TableProxySqlServerv2k5 class="oracle.dbtools.crest.model.design.storage.sqlserver.v2k5.TableProxySqlServerv2k5" name="USMC.No..ca.onType" directorySegmentName="seg_1" id="864EC87B-FDFC-C6D6-1D02-F6896CBAF469">
<createdBy>MichalBonino</createdBy>
<createdTime>2024-04-29 23:41:56 UTC</createdTime>
<ownerDesignName>MCRISSLegacyModel</ownerDesignName>
<database>7220F1F8-DA6B-58D6-61AE-B77688E1C655</database>
<schema>484282A5-7879-9C7B-90F3-AE69A95D4557</schema>
<columnProxies>
<ColumnProxy class="oracle.dbtools.crest.model.design.storage.sqlserver.v2k12.ColumnProxySqlServerv2k12" name="No..ca.onType" id="7511760A-20B1-5166-7168-8B84F21BB152">
<createdBy>MichalBonino</createdBy>
<createdTime>2024-04-29 23:42:11 UTC</createdTime>
<ownerDesignName>MCRISSLegacyModel</ownerDesignName>
</ColumnProxy>
<ColumnProxy class="oracle.dbtools.crest.model.design.storage.sqlserver.v2k12.ColumnProxySqlServerv2k12" name="No..ca.onTypeID" id="C62457C9-37CA-5CA6-8B6E-B60EFE23DF85">
<createdBy>MichalBonino</createdBy>
<createdTime>2024-04-29 23:42:11 UTC</createdTime>
<ownerDesignName>MCRISSLegacyModel</ownerDesignName>
<asIdentity>true</asIdentity>
<identityForReplication>YES</identityForReplication>
</ColumnProxy>
</columnProxies>
<primaryKeys>
<PrimaryKey class="oracle.dbtools.crest.model.design.storage.sqlserver.v2k5.PKProxySqlServerv2k5" name="No..ca.onType_PK" id="425F8EA7-0597-9E91-CA0A-F5DAE24F83F9">
<createdBy>MichalBonino</createdBy>
<createdTime>2024-04-29 23:42:11 UTC</createdTime>
<ownerDesignName>MCRISSLegacyModel</ownerDesignName>
<clustered>true</clustered>
<fillFactor>100</fillFactor>
<partitioningColumn>35A09DA7-D379-0FF0-191F-49F6AE4545C6</partitioningColumn>
</PrimaryKey>
</primaryKeys>
</TableProxySqlServerv2k5>