<?xml version = '1.0' encoding = 'UTF-8'?>
<StoredProcedureSqlServerv2k5 class="oracle.dbtools.crest.model.design.storage.sqlserver.v2k5.StoredProcedureSqlServerv2k5" name="[sp_MILogFilename]" directorySegmentName="seg_0" id="64339B47-7BA6-2ACF-A53C-6A86A338A674">
<sourceDDLFile>Appian.sql</sourceDDLFile>
<createdBy>MichalBonino</createdBy>
<createdTime>2024-04-29 23:57:09 UTC</createdTime>
<ownerDesignName>MCRISSLegacyModel</ownerDesignName>
<body><![CDATA[( 
  @FILE_NAME char (40) 
 ) 
  
AS 
 
 INSERT INTO dbo.MIRS_FILENAME_LOG ( 
  [FILE_NAME], 
  [STATUS], 
  [LOG_DATE], 
  [FINISH_DATE], 
  [USER_LOGIN], 
  [UPDATE_DATE] 
  ) 
 VALUES 
 ( 
  @FILE_NAME, 
  'WORKING', 
  GETDATE(), 
  GETDATE(), 
  'MIRS_INTERFACE', 
  GETDATE() 
 )]]></body>
<schema>DD6CF638-A2EB-2E1B-FF13-422CA718DE2D</schema>
<database>24B9F7BA-5DD4-EAB5-4EB1-35B911743E85</database>
</StoredProcedureSqlServerv2k5>