<?xml version = '1.0' encoding = 'UTF-8'?>
<FKIndexAssociation class="oracle.dbtools.crest.model.design.relational.FKIndexAssociation" directorySegmentName="seg_0" id="FE24CCEE-F312-6179-8CEA-7D9270DA50CE" containerWithKeyObject="D581B810-5DFC-EEC2-F208-9AF625B15EA8" localFKIndex="5A11D814-D33F-392C-B090-1C5CCDC5B515" name="._retrain_unitAdminchief_rankid">
<sourceDDLFile>create PSR script - MCRISS OTA.txt</sourceDDLFile>
<createdBy>MichalBonino</createdBy>
<createdTime>2024-04-29 23:43:25 UTC</createdTime>
<ownerDesignName>MCRISSLegacyModel</ownerDesignName>
<importedID>32BB6626-C863-2D2A-D680-E6278AAB654A</importedID>
<referredTableLongName>dbo.Rank</referredTableLongName>
<deleteRule>NO ACTION</deleteRule>
<referredTableID>19867CF0-30E2-1CB9-89E6-FD53BC8B8756</referredTableID>
<keyObject>C065257C-CBB1-22F1-D8DD-5A3B455D5344</keyObject>
<referredKeyID>C065257C-CBB1-22F1-D8DD-5A3B455D5344</referredKeyID>
<mandatory>false</mandatory>
<refColNames>RankID</refColNames>
<transferable>true</transferable>
<rely>false</rely>
<columnDependencyConstraintGenerateInDDL>true</columnDependencyConstraintGenerateInDDL>
</FKIndexAssociation>