<?xml version = '1.0' encoding = 'UTF-8'?>
<FKIndexAssociation class="oracle.dbtools.crest.model.design.relational.FKIndexAssociation" directorySegmentName="seg_3" id="9592BEE4-67AB-2606-A91F-BB8224E34609" containerWithKeyObject="191AA48C-AC05-1017-5915-1A75B673561B" localFKIndex="98E83C71-7303-DF9E-9544-D50532C646FD" name="SignatureVault_FK0">
<sourceDDLFile>create RSSOSS script - MCRISS OTA.txt</sourceDDLFile>
<createdBy>MichalBonino</createdBy>
<createdTime>2024-04-29 23:42:13 UTC</createdTime>
<ownerDesignName>MCRISSLegacyModel</ownerDesignName>
<importedID>19CFE22D-1491-36AE-586B-F749DA32D5A1</importedID>
<referredTableLongName>USMC.VaultContentType</referredTableLongName>
<deleteRule>NO ACTION</deleteRule>
<referredTableID>3DA59AA6-4524-2911-7AF5-3FC31E995313</referredTableID>
<keyObject>54564FC2-263C-4AB1-D628-5DBA8D911BC6</keyObject>
<referredKeyID>54564FC2-263C-4AB1-D628-5DBA8D911BC6</referredKeyID>
<mandatory>true</mandatory>
<refColNames>ID</refColNames>
<transferable>true</transferable>
<rely>false</rely>
<columnDependencyConstraintGenerateInDDL>true</columnDependencyConstraintGenerateInDDL>
</FKIndexAssociation>