<?xml version = '1.0' encoding = 'UTF-8'?>
<FKIndexAssociation class="oracle.dbtools.crest.model.design.relational.FKIndexAssociation" directorySegmentName="seg_3" id="983BC14D-00B1-7537-8870-9C531D33F09A" containerWithKeyObject="D38CFAA8-97D9-6E73-BEAD-6BEBEB875197" localFKIndex="FECC69B8-C45C-48EF-177A-DE58F104A320" name="FK_MedicalInfo_Applicant">
<sourceDDLFile>create ACP script - MCRISS OTA.txt</sourceDDLFile>
<createdBy>MichalBonino</createdBy>
<createdTime>2024-04-30 00:00:03 UTC</createdTime>
<ownerDesignName>MCRISSLegacy</ownerDesignName>
<importedID>0763B016-0641-FC55-7DCB-C8BA7F579B23</importedID>
<referredTableLongName>ACP.Applicant</referredTableLongName>
<deleteRule>NO ACTION</deleteRule>
<referredTableID>76BC4A4F-A847-DA19-C2DF-732063763C50</referredTableID>
<keyObject>5DD98CB6-4C9B-6D10-601E-21885B60DED7</keyObject>
<referredKeyID>5DD98CB6-4C9B-6D10-601E-21885B60DED7</referredKeyID>
<mandatory>true</mandatory>
<refColNames>PersonId</refColNames>
<transferable>true</transferable>
<rely>false</rely>
<columnDependencyConstraintGenerateInDDL>true</columnDependencyConstraintGenerateInDDL>
</FKIndexAssociation>