<?xml version = '1.0' encoding = 'UTF-8'?>
<Diagram class="oracle.dbtools.crest.swingui.relational.DPVRelationalSubView" name="Relational_1 - SubView_1" id="EFADC384-C64B-94BD-8452-B855C300A083">
<createdBy>MichalBonino</createdBy>
<modifiedBy>MichalBonino</modifiedBy>
<createdTime>2024-05-01 15:41:59 UTC</createdTime>
<autoRoute>false</autoRoute>
<boxInbox>true</boxInbox>
<showLegend>false</showLegend>
<showLabels>false</showLabels>
<showRelAttributes>false</showRelAttributes>
<gridEnabled>false</gridEnabled>
<showGrid>false</showGrid>
<diagramColor>-1</diagramColor>
<display>false</display>
<notation>1</notation>
<objectViews>
<OView class="oracle.dbtools.crest.swingui.relational.TVTable" oid="60C46418-0630-79BA-2171-3B8C0E104D18" otype="Table" vid="BA382F0D-4066-B057-71F8-8BE16CE2C34A">
<hideElementsInCurrentOnly>false</hideElementsInCurrentOnly>
<bounds x="20" y="20" width="461" height="408"/>
</OView>
<OView class="oracle.dbtools.crest.swingui.relational.TVTable" oid="65DC0A2D-63C4-27B8-E4C9-586A10E02E56" otype="Table" vid="FC06981D-E186-5309-AC6B-4DBAAE23E558">
<hideElementsInCurrentOnly>false</hideElementsInCurrentOnly>
<bounds x="7" y="492" width="307" height="158"/>
</OView>
<OView class="oracle.dbtools.crest.swingui.TVNote" oid="A176B320-472A-1772-09CA-6A690CB3DAC3" otype="Note" vid="8A861B69-C48D-8981-9E8C-C7052AB577FF">
<hideElementsInCurrentOnly>false</hideElementsInCurrentOnly>
<bounds x="665" y="80" width="95" height="40"/>
<comment>This is a note.</comment>
</OView>
<OView class="oracle.dbtools.crest.swingui.relational.TVTable" oid="DE2DB23D-4DAE-43C6-8A52-02E6D3590065" otype="Table" vid="33F243F0-18FB-C24C-F5A5-2E2DA57A8CD0">
<hideElementsInCurrentOnly>false</hideElementsInCurrentOnly>
<bounds x="335" y="489" width="389" height="3876"/>
</OView>
<OView class="oracle.dbtools.crest.swingui.relational.TVTable" oid="E2D6F44C-5DD2-37B1-09DB-5AAD208B936B" otype="Table" vid="70A7B9D3-69AB-2A20-B1E4-0BAE710C7C35">
<hideElementsInCurrentOnly>false</hideElementsInCurrentOnly>
<bounds x="523" y="290" width="179" height="74"/>
</OView>
<OView class="oracle.dbtools.crest.swingui.relational.TVTable" oid="EF550390-F8B0-6225-A7AD-58847A6288FB" otype="Table" vid="620B5631-DE50-2D23-B54C-0245A4932B29">
<hideElementsInCurrentOnly>false</hideElementsInCurrentOnly>
<bounds x="821" y="355" width="283" height="2266"/>
</OView>
</objectViews>
</Diagram>