<?xml version = '1.0' encoding = 'UTF-8'?>
<TableProxySqlServerv2k5 class="oracle.dbtools.crest.model.design.storage.sqlserver.v2k5.TableProxySqlServerv2k5" name="ARMS_OFFICER_UPDATE" directorySegmentName="seg_6" id="93C37DE6-14EC-BD92-C50B-DDD71AD5199D">
<createdBy>MichalBonino</createdBy>
<createdTime>2024-04-29 19:29:12 UTC</createdTime>
<ownerDesignName>MCRISSLegacy</ownerDesignName>
<schemaObject>2A6D9360-3BB2-5CEA-6E99-790D76996FDF</schemaObject>
<database>B007042D-D2E3-F83F-481F-CEB23B21CB30</database>
<filegroup>E6573514-5674-5781-6648-B1C5FB42B0A5</filegroup>
<schema>3925E19F-DC76-90A4-B892-D7A526C79632</schema>
<columnProxies>
<ColumnProxy class="oracle.dbtools.crest.model.design.storage.sqlserver.v2k12.ColumnProxySqlServerv2k12" name="Acty_Rctd_Frm" id="1556DB80-6CFD-2F6C-52F4-A60AAFD7FD09">
<createdBy>MichalBonino</createdBy>
<createdTime>2024-04-29 19:29:15 UTC</createdTime>
<ownerDesignName>MCRISSLegacy</ownerDesignName>
</ColumnProxy>
<ColumnProxy class="oracle.dbtools.crest.model.design.storage.sqlserver.v2k12.ColumnProxySqlServerv2k12" name="LSAT" id="1B73A9E9-623E-548B-F325-37AEF37C007E">
<createdBy>MichalBonino</createdBy>
<createdTime>2024-04-29 19:29:15 UTC</createdTime>
<ownerDesignName>MCRISSLegacy</ownerDesignName>
</ColumnProxy>
<ColumnProxy class="oracle.dbtools.crest.model.design.storage.sqlserver.v2k12.ColumnProxySqlServerv2k12" name="SRC_Rctd_Frm" id="239B2587-7EC1-F47D-6C8C-9D9CA318F1C3">
<createdBy>MichalBonino</createdBy>
<createdTime>2024-04-29 19:29:15 UTC</createdTime>
<ownerDesignName>MCRISSLegacy</ownerDesignName>
</ColumnProxy>
<ColumnProxy class="oracle.dbtools.crest.model.design.storage.sqlserver.v2k12.ColumnProxySqlServerv2k12" name="OSO_Rank" id="248B3E43-81C8-7B6D-3E6B-2C1FBB51D817">
<createdBy>MichalBonino</createdBy>
<createdTime>2024-04-29 19:29:15 UTC</createdTime>
<ownerDesignName>MCRISSLegacy</ownerDesignName>
</ColumnProxy>
<ColumnProxy class="oracle.dbtools.crest.model.design.storage.sqlserver.v2k12.ColumnProxySqlServerv2k12" name="PFT" id="37D5CB90-38FD-235E-EEE3-80E2C7DEF84F">
<createdBy>MichalBonino</createdBy>
<createdTime>2024-04-29 19:29:15 UTC</createdTime>
<ownerDesignName>MCRISSLegacy</ownerDesignName>
</ColumnProxy>
<ColumnProxy class="oracle.dbtools.crest.model.design.storage.sqlserver.v2k12.ColumnProxySqlServerv2k12" name="OSS (MCC_CODE)" id="3D186C04-E03F-81C9-3CD1-F10C53F70E92">
<createdBy>MichalBonino</createdBy>
<createdTime>2024-04-29 19:29:15 UTC</createdTime>
<ownerDesignName>MCRISSLegacy</ownerDesignName>
</ColumnProxy>
<ColumnProxy class="oracle.dbtools.crest.model.design.storage.sqlserver.v2k12.ColumnProxySqlServerv2k12" name="Curr_Grad_Dte" id="4CAE5DBE-2846-946B-0DE2-C7D1ADF899F7">
<createdBy>MichalBonino</createdBy>
<createdTime>2024-04-29 19:29:15 UTC</createdTime>
<ownerDesignName>MCRISSLegacy</ownerDesignName>
</ColumnProxy>
<ColumnProxy class="oracle.dbtools.crest.model.design.storage.sqlserver.v2k12.ColumnProxySqlServerv2k12" name="Dist" id="6335111D-30CE-7385-A971-BFEBC096C7C6">
<createdBy>MichalBonino</createdBy>
<createdTime>2024-04-29 19:29:15 UTC</createdTime>
<ownerDesignName>MCRISSLegacy</ownerDesignName>
</ColumnProxy>
<ColumnProxy class="oracle.dbtools.crest.model.design.storage.sqlserver.v2k12.ColumnProxySqlServerv2k12" name="Proj_Comm_Dte" id="677AF5BE-EFEF-2734-5DC3-EB622104DF61">
<createdBy>MichalBonino</createdBy>
<createdTime>2024-04-29 19:29:15 UTC</createdTime>
<ownerDesignName>MCRISSLegacy</ownerDesignName>
</ColumnProxy>
<ColumnProxy class="oracle.dbtools.crest.model.design.storage.sqlserver.v2k12.ColumnProxySqlServerv2k12" name="Height" id="75B8C3C5-504E-4C9F-729A-B3E713C25506">
<createdBy>MichalBonino</createdBy>
<createdTime>2024-04-29 19:29:15 UTC</createdTime>
<ownerDesignName>MCRISSLegacy</ownerDesignName>
</ColumnProxy>
<ColumnProxy class="oracle.dbtools.crest.model.design.storage.sqlserver.v2k12.ColumnProxySqlServerv2k12" name="OSO_MI" id="83956739-64D7-1CF8-062C-DCCB0A89A2F7">
<createdBy>MichalBonino</createdBy>
<createdTime>2024-04-29 19:29:15 UTC</createdTime>
<ownerDesignName>MCRISSLegacy</ownerDesignName>
</ColumnProxy>
<ColumnProxy class="oracle.dbtools.crest.model.design.storage.sqlserver.v2k12.ColumnProxySqlServerv2k12" name="Contract_Dte" id="85991977-19DE-55EC-004B-258CDD1740CA">
<createdBy>MichalBonino</createdBy>
<createdTime>2024-04-29 19:29:15 UTC</createdTime>
<ownerDesignName>MCRISSLegacy</ownerDesignName>
</ColumnProxy>
<ColumnProxy class="oracle.dbtools.crest.model.design.storage.sqlserver.v2k12.ColumnProxySqlServerv2k12" name="OSO_First_Name" id="87C45080-D43F-1808-0A30-C4238E22F56B">
<createdBy>MichalBonino</createdBy>
<createdTime>2024-04-29 19:29:15 UTC</createdTime>
<ownerDesignName>MCRISSLegacy</ownerDesignName>
</ColumnProxy>
<ColumnProxy class="oracle.dbtools.crest.model.design.storage.sqlserver.v2k12.ColumnProxySqlServerv2k12" name="First_Name" id="8EA73579-8184-13AB-0709-AFDB49C47954">
<createdBy>MichalBonino</createdBy>
<createdTime>2024-04-29 19:29:15 UTC</createdTime>
<ownerDesignName>MCRISSLegacy</ownerDesignName>
</ColumnProxy>
<ColumnProxy class="oracle.dbtools.crest.model.design.storage.sqlserver.v2k12.ColumnProxySqlServerv2k12" name="Coll_Ed_Level" id="94D068A5-3368-8AF4-E50D-BF7D9C4D2878">
<createdBy>MichalBonino</createdBy>
<createdTime>2024-04-29 19:29:15 UTC</createdTime>
<ownerDesignName>MCRISSLegacy</ownerDesignName>
</ColumnProxy>
<ColumnProxy class="oracle.dbtools.crest.model.design.storage.sqlserver.v2k12.ColumnProxySqlServerv2k12" name="MCC_CODE" id="A5770E6C-2647-26F6-89C6-2E0FBED70C97">
<createdBy>MichalBonino</createdBy>
<createdTime>2024-04-29 19:29:15 UTC</createdTime>
<ownerDesignName>MCRISSLegacy</ownerDesignName>
</ColumnProxy>
<ColumnProxy class="oracle.dbtools.crest.model.design.storage.sqlserver.v2k12.ColumnProxySqlServerv2k12" name="OSO_Last_Name" id="AE2D2120-7AA7-3BEF-0F20-792E39896ED2">
<createdBy>MichalBonino</createdBy>
<createdTime>2024-04-29 19:29:15 UTC</createdTime>
<ownerDesignName>MCRISSLegacy</ownerDesignName>
</ColumnProxy>
<ColumnProxy class="oracle.dbtools.crest.model.design.storage.sqlserver.v2k12.ColumnProxySqlServerv2k12" name="Last_Name" id="AEB433C7-7577-6180-BE2D-029179B4E679">
<createdBy>MichalBonino</createdBy>
<createdTime>2024-04-29 19:29:15 UTC</createdTime>
<ownerDesignName>MCRISSLegacy</ownerDesignName>
</ColumnProxy>
<ColumnProxy class="oracle.dbtools.crest.model.design.storage.sqlserver.v2k12.ColumnProxySqlServerv2k12" name="RSN" id="B6EEB52C-CAA4-9639-450E-948A50CA45DA">
<createdBy>MichalBonino</createdBy>
<createdTime>2024-04-29 19:29:15 UTC</createdTime>
<ownerDesignName>MCRISSLegacy</ownerDesignName>
</ColumnProxy>
<ColumnProxy class="oracle.dbtools.crest.model.design.storage.sqlserver.v2k12.ColumnProxySqlServerv2k12" name="OSO_SSN" id="C84F65AE-ADD4-010F-9031-640759B944F4">
<createdBy>MichalBonino</createdBy>
<createdTime>2024-04-29 19:29:15 UTC</createdTime>
<ownerDesignName>MCRISSLegacy</ownerDesignName>
</ColumnProxy>
<ColumnProxy class="oracle.dbtools.crest.model.design.storage.sqlserver.v2k12.ColumnProxySqlServerv2k12" name="Sex" id="DB47BB3C-123D-BE5C-6365-361CBFC687AA">
<createdBy>MichalBonino</createdBy>
<createdTime>2024-04-29 19:29:15 UTC</createdTime>
<ownerDesignName>MCRISSLegacy</ownerDesignName>
</ColumnProxy>
<ColumnProxy class="oracle.dbtools.crest.model.design.storage.sqlserver.v2k12.ColumnProxySqlServerv2k12" name="Org_ID" id="DECED798-979F-EDBD-67C8-C6E5E2350047">
<createdBy>MichalBonino</createdBy>
<createdTime>2024-04-29 19:29:15 UTC</createdTime>
<ownerDesignName>MCRISSLegacy</ownerDesignName>
</ColumnProxy>
<ColumnProxy class="oracle.dbtools.crest.model.design.storage.sqlserver.v2k12.ColumnProxySqlServerv2k12" name="Weight" id="EF8E81A2-94C4-47C3-C79A-7B076D022790">
<createdBy>MichalBonino</createdBy>
<createdTime>2024-04-29 19:29:15 UTC</createdTime>
<ownerDesignName>MCRISSLegacy</ownerDesignName>
</ColumnProxy>
<ColumnProxy class="oracle.dbtools.crest.model.design.storage.sqlserver.v2k12.ColumnProxySqlServerv2k12" name="SSN" id="F397377C-2E18-347E-7074-01820E34E0FF">
<createdBy>MichalBonino</createdBy>
<createdTime>2024-04-29 19:29:15 UTC</createdTime>
<ownerDesignName>MCRISSLegacy</ownerDesignName>
</ColumnProxy>
<ColumnProxy class="oracle.dbtools.crest.model.design.storage.sqlserver.v2k12.ColumnProxySqlServerv2k12" name="SAT" id="F46BF9F5-7E75-BE4C-998B-13D6F7257C20">
<createdBy>MichalBonino</createdBy>
<createdTime>2024-04-29 19:29:15 UTC</createdTime>
<ownerDesignName>MCRISSLegacy</ownerDesignName>
</ColumnProxy>
<ColumnProxy class="oracle.dbtools.crest.model.design.storage.sqlserver.v2k12.ColumnProxySqlServerv2k12" name="GPA" id="F6E78E66-1874-AA82-A984-2B8B1DF37231">
<createdBy>MichalBonino</createdBy>
<createdTime>2024-04-29 19:29:15 UTC</createdTime>
<ownerDesignName>MCRISSLegacy</ownerDesignName>
</ColumnProxy>
<ColumnProxy class="oracle.dbtools.crest.model.design.storage.sqlserver.v2k12.ColumnProxySqlServerv2k12" name="Comm_Dte" id="FC647F13-6682-768D-320C-FA11DB1CDEAD">
<createdBy>MichalBonino</createdBy>
<createdTime>2024-04-29 19:29:15 UTC</createdTime>
<ownerDesignName>MCRISSLegacy</ownerDesignName>
</ColumnProxy>
<ColumnProxy class="oracle.dbtools.crest.model.design.storage.sqlserver.v2k12.ColumnProxySqlServerv2k12" name="ACT" id="FDA14364-67E5-82F1-8C71-CB72B8929DC6">
<createdBy>MichalBonino</createdBy>
<createdTime>2024-04-29 19:29:15 UTC</createdTime>
<ownerDesignName>MCRISSLegacy</ownerDesignName>
</ColumnProxy>
</columnProxies>
</TableProxySqlServerv2k5>