<?xml version = '1.0' encoding = 'UTF-8'?>
<FKIndexAssociation class="oracle.dbtools.crest.model.design.relational.FKIndexAssociation" directorySegmentName="seg_1" id="84FA7F76-4FBC-2E5E-BD64-2F04844253E6" containerWithKeyObject="3283C85E-E240-6ED8-E577-66A4A69C5F66" localFKIndex="E0422BD2-C23D-AA84-C806-7BE690D0F96A" name="EventBudget_FK0">
<sourceDDLFile>create RSSOSS script - MCRISS OTA.txt</sourceDDLFile>
<createdBy>MichalBonino</createdBy>
<createdTime>2024-04-29 23:42:13 UTC</createdTime>
<ownerDesignName>MCRISSLegacyModel</ownerDesignName>
<importedID>884F75D4-659E-ED93-E05E-2C189C175E03</importedID>
<referredTableLongName>USMC.Event</referredTableLongName>
<deleteRule>NO ACTION</deleteRule>
<referredTableID>66AC9909-F23E-1468-B894-6B629EA533EC</referredTableID>
<keyObject>EAED351D-97EE-FE25-DF56-1B3A9B19B3F6</keyObject>
<referredKeyID>EAED351D-97EE-FE25-DF56-1B3A9B19B3F6</referredKeyID>
<mandatory>true</mandatory>
<refColNames>ID</refColNames>
<transferable>true</transferable>
<rely>false</rely>
<columnDependencyConstraintGenerateInDDL>true</columnDependencyConstraintGenerateInDDL>
</FKIndexAssociation>