<?xml version = '1.0' encoding = 'UTF-8'?>
<FKIndexAssociation class="oracle.dbtools.crest.model.design.relational.FKIndexAssociation" directorySegmentName="seg_1" id="9D4055D9-78DF-07F3-F877-473A062DA946" containerWithKeyObject="79274D7B-FB0B-994C-83A4-1CAA5BF0DBE6" localFKIndex="F34F39B5-C7B2-492A-EDD0-A49E0FECAF9B" name="FK_EventPlan_EventSource">
<sourceDDLFile>create RSSOSS script - MCRISS OTA.txt</sourceDDLFile>
<createdBy>MichalBonino</createdBy>
<createdTime>2024-04-29 23:42:13 UTC</createdTime>
<ownerDesignName>MCRISSLegacyModel</ownerDesignName>
<importedID>65AD1C62-7FD0-5789-6DE3-811922FE2E88</importedID>
<referredTableLongName>USMC.EventSource</referredTableLongName>
<deleteRule>NO ACTION</deleteRule>
<referredTableID>B5285577-85B2-2C10-5FB4-6B622741A586</referredTableID>
<keyObject>80DA941E-D194-A100-BE92-0CE788AF3695</keyObject>
<referredKeyID>80DA941E-D194-A100-BE92-0CE788AF3695</referredKeyID>
<mandatory>true</mandatory>
<refColNames>ID</refColNames>
<transferable>true</transferable>
<rely>false</rely>
<columnDependencyConstraintGenerateInDDL>true</columnDependencyConstraintGenerateInDDL>
</FKIndexAssociation>