<?xml version = '1.0' encoding = 'UTF-8'?>
<StoredProcedureSqlServerv2k5 class="oracle.dbtools.crest.model.design.storage.sqlserver.v2k5.StoredProcedureSqlServerv2k5" name="[sp_UpdateSMCR]" directorySegmentName="seg_25" id="36AE4C2A-544C-DD4F-C179-30CAC868632B">
<sourceDDLFile>create MCRISS script - MCRISS OTA.txt</sourceDDLFile>
<createdBy>MichalBonino</createdBy>
<createdTime>2024-04-29 19:28:42 UTC</createdTime>
<ownerDesignName>MCRISSLegacyModel</ownerDesignName>
<body><![CDATA[@SMCRID   int   = 0, 
 @ContractID  int, 
 @Ac.vated  char(1), 
 @Ac.vatedDate  date.me, 
 @Deac.vatedDate date.me  = NULL, 
 @UserLogin  varchar(15), 
 @ID   int   = 0 OUTPUT 
AS 
 
IF EXISTS (SELECT 1 FROM SMCR WHERE SMCR_ID = @SMCRID) 
BEGIN 
 UPDATE 
  SMCR 
 SET 
  CONTRACT_ID   = @ContractID, 
  ACTIVATED  = @Ac.vated, 
  ACTIVATED_DATE  = @Ac.vatedDate, 
  DEACTIVATED_DATE = @Deac.vatedDate, 
  USER_LOGIN  = @UserLogin, 
  UPDATE_DATE  = GETDATE() 
 WHERE 
  SMCR_ID   = @SMCRID 
 
 --- RETURN THE SMCR ID 
 SET @ID = @SMCRID 
END 
ELSE 
BEGIN 
 INSERT INTO SMCR  
  (CONTRACT_ID, ACTIVATED, ACTIVATED_DATE, DEACTIVATED_DATE, USER_LOGIN, UPDATE_DATE) 
 VALUES 
  (@ContractID, @Ac.vated, @Ac.vatedDate, @Deac.vatedDate, @UserLogin, GETDATE()) 
 
 --- RETURN THE SMCR ID 
 SET @ID = @@IDENTITY 
END]]></body>
<schema>3925E19F-DC76-90A4-B892-D7A526C79632</schema>
<database>B007042D-D2E3-F83F-481F-CEB23B21CB30</database>
</StoredProcedureSqlServerv2k5>